runtime_docstrings/__init__.py
runtime_docstrings/_parser.py
runtime_docstrings/py.typed
runtime_docstrings-0.1.3.dist-info/WHEEL
runtime_docstrings-0.1.3.dist-info/METADATA
runtime_docstrings-0.1.3.dist-info/RECORD
