Metadata-Version: 2.4
Name: runtime-docstrings
Version: 0.1.3
Summary: Runtime access to Python class attribute docstrings (PEP 224)
Keywords: docstrings,PEP 224,pep224,class attributes,error reporting,enum,dataclasses,ast,sphinx,autodoc
Author: gesslerpd
Author-email: gesslerpd <gesslerpd@users.noreply.github.com>
License-Expression: MIT
Requires-Python: >=3.10
Project-URL: Homepage, https://github.com/gesslerpd/runtime-docstrings
Project-URL: Issues, https://github.com/gesslerpd/runtime-docstrings/issues
Project-URL: Repository, https://github.com/gesslerpd/runtime-docstrings
